aubio/__init__.py
aubio/_aubio.so
aubio/midiconv.py
aubio/slicing.py
aubio-0.4.3a2.data/scripts/aubiocut
aubio-0.4.3a2.dist-info/DESCRIPTION.rst
aubio-0.4.3a2.dist-info/METADATA
aubio-0.4.3a2.dist-info/RECORD
aubio-0.4.3a2.dist-info/WHEEL
aubio-0.4.3a2.dist-info/metadata.json
aubio-0.4.3a2.dist-info/top_level.txt
